cookie_clicker_parser/__init__.py
cookie_clicker_parser/parser.py
cookie_clicker_parser/section_parsers.py
cookie_clicker_parser-1.1.0.dist-info/LICENSE
cookie_clicker_parser-1.1.0.dist-info/METADATA
cookie_clicker_parser-1.1.0.dist-info/WHEEL
cookie_clicker_parser-1.1.0.dist-info/top_level.txt
cookie_clicker_parser-1.1.0.dist-info/RECORD
