Metadata-Version: 2.1
Name: cookie-clicker-parser
Version: 1.1.0
Summary: Parser for Cookie Clicker save codes
Home-page: https://github.com/ShadowCrafter011/Cookie-Clicker-Parser
Author: ShadowCrafter
License: MIT
Keywords: parser,cookie clicker
License-File: LICENSE
